yaqd_seabreeze/VERSION
yaqd_seabreeze/__init__.py
yaqd_seabreeze/__version__.py
yaqd_seabreeze/_seabreeze.py
yaqd_seabreeze/_seabreeze_script.py
yaqd_seabreeze/seabreeze-script.avpr
yaqd_seabreeze/seabreeze-script.toml
yaqd_seabreeze/seabreeze.avpr
yaqd_seabreeze/seabreeze.toml
yaqd_seabreeze-2025.4.0.dist-info/entry_points.txt
yaqd_seabreeze-2025.4.0.dist-info/licenses/LICENSE
yaqd_seabreeze-2025.4.0.dist-info/WHEEL
yaqd_seabreeze-2025.4.0.dist-info/METADATA
yaqd_seabreeze-2025.4.0.dist-info/RECORD
