Metadata-Version: 2.4
Name: yaqd-seabreeze
Version: 2025.4.0
Summary: yaq daemons for Ocean Optics spectrometers
Author-email: Blaise Thompson <blaise@untzag.com>
Maintainer: yaq Developers
Requires-Python: >=3.7
Classifier: Development Status :: 4 - Beta
Classifier: Intended Audience :: Science/Research
Classifier: License :: OSI Approved :: GNU Lesser General Public License v3 (LGPLv3)
Classifier: Natural Language :: English
Classifier: Programming Language :: Python :: 3
Classifier: Programming Language :: Python :: 3.9
Classifier: Programming Language :: Python :: 3.10
Classifier: Programming Language :: Python :: 3.11
Classifier: Programming Language :: Python :: 3.12
Classifier: Topic :: Scientific/Engineering
License-File: LICENSE
Requires-Dist: yaqd-core>=2021.3.0
Requires-Dist: seabreeze
Requires-Dist: pyusb
Requires-Dist: numpy
Requires-Dist: black ; extra == "dev"
Requires-Dist: pre-commit ; extra == "dev"
Project-URL: Homepage, https://yaq.fyi
Project-URL: Issues, https://github.com/yaq-project/yaqd-seabreeze/issues
Project-URL: Source, https://github.com/yaq-project/yaqd-seabreeze
Provides-Extra: dev
